fucc/__init__.py
fucc/inductive_step.py
fucc/metrics.py
fucc/model_selection.py
fucc/pagerank.py
fucc/utils.py
fucc-0.0.8.dist-info/LICENSE
fucc-0.0.8.dist-info/METADATA
fucc-0.0.8.dist-info/WHEEL
fucc-0.0.8.dist-info/top_level.txt
fucc-0.0.8.dist-info/RECORD
