Metadata-Version: 2.1
Name: fucc
Version: 0.0.8
Summary: Fraudulent Use of Credit Card
Home-page: https://github.com/rafaelvanbelle/fucc_package
Author: Rafael Van Belle
Author-email: rafael@gmail.com
License: UNKNOWN
Platform: UNKNOWN
Classifier: Programming Language :: Python :: 3
Classifier: License :: OSI Approved :: MIT License
Classifier: Operating System :: OS Independent
Requires-Python: >=3.6
License-File: LICENSE
Requires-Dist: scikit-learn
Requires-Dist: pandas
Requires-Dist: tqdm
Requires-Dist: scikit-plot
Requires-Dist: matplotlib
Requires-Dist: networkx
Requires-Dist: dateparser
